AUTHORS
HISTORY.rst
LICENSE
MANIFEST.in
NOTICE
README.rst
setup.py
juggling/__init__.py
juggling/utils.py
juggling/notation/__init__.py
juggling/notation/base.py
juggling/notation/siteswap.py
juggling/pattern/__init__.py
pyjuggling.egg-info/PKG-INFO
pyjuggling.egg-info/SOURCES.txt
pyjuggling.egg-info/dependency_links.txt
pyjuggling.egg-info/top_level.txt